beancount_payeeverif.py
beancount_payeeverif-1.0.2.dist-info/LICENSE
beancount_payeeverif-1.0.2.dist-info/METADATA
beancount_payeeverif-1.0.2.dist-info/WHEEL
beancount_payeeverif-1.0.2.dist-info/top_level.txt
beancount_payeeverif-1.0.2.dist-info/RECORD
