Metadata-Version: 2.1
Name: beancount-payeeverif
Version: 1.0.2
Summary: Payee verification plugin for Beancount
Home-page: https://github.com/siriobalmelli/beancount_payeeverif
Author: Sirio Balmelli
Author-email: sirio@b-ad.ch
License: MIT
Keywords: plugins double-entry beancount accounting document verification
Platform: UNKNOWN
Classifier: Development Status :: 5 - Production/Stable
Classifier: Intended Audience :: Financial and Insurance Industry
Classifier: License :: OSI Approved :: MIT License
Classifier: Natural Language :: English
Classifier: Operating System :: OS Independent
Classifier: Programming Language :: Python :: 3 :: Only
Classifier: Programming Language :: Python :: 3.6
Classifier: Programming Language :: Python :: 3.7
Classifier: Programming Language :: Python :: 3.8
Classifier: Programming Language :: Python :: 3.9
Classifier: Topic :: Office/Business :: Financial :: Accounting
Classifier: Topic :: Office/Business :: Financial :: Investment
License-File: LICENSE
Requires-Dist: beancount
Provides-Extra: dev
Requires-Dist: pytest ; extra == 'dev'
Requires-Dist: tox ; extra == 'dev'
